{
    "Stretchly": {
        "sha256": "1xn0jrm75pk1hhadk6ikmjgcqlw54physc5q4xaipxl6aashkcjl",
        "type": "file",
        "url": "https://github.com/hovancik/stretchly/releases/download/v1.2.0/Stretchly-1.2.0.dmg",
        "url_template": "https://github.com/hovancik/stretchly/releases/download/v<version>/Stretchly-<version>.dmg",
        "version": "1.2.0"
    },
    "home-manager": {
        "branch": "master",
        "description": "Manage a user environment using Nix  [maintainer=@rycee] ",
        "homepage": "https://rycee.gitlab.io/home-manager/",
        "owner": "nix-community",
        "repo": "home-manager",
        "rev": "b5847455066d0191cebd6b140531cc154443e316",
        "sha256": "05jnpwhqcq3b0q555awv84cqmmnzg4hlnms8hjkw9661qw6827s2",
        "type": "tarball",
        "url": "https://github.com/nix-community/home-manager/archive/b5847455066d0191cebd6b140531cc154443e316.tar.gz",
        "url_template": "https://github.com/<owner>/<repo>/archive/<rev>.tar.gz"
    },
    "hosts": {
        "branch": "master",
        "description": "Consolidating and extending hosts files from several well-curated sources. You can optionally pick extensions to block pornography, social media, and other categories.",
        "homepage": "",
        "owner": "StevenBlack",
        "repo": "hosts",
        "rev": "5a5016ab5bf0166e004147cb49ccd0114ed29b72",
        "sha256": "07pjj28bqpn5ldh8f49n3m99ifwq1r24sqkvlfb19pgahirnd3ws",
        "type": "tarball",
        "url": "https://github.com/StevenBlack/hosts/archive/5a5016ab5bf0166e004147cb49ccd0114ed29b72.tar.gz",
        "url_template": "https://github.com/<owner>/<repo>/archive/<rev>.tar.gz"
    },
    "niv": {
        "branch": "master",
        "description": "Easy dependency management for Nix projects",
        "homepage": "https://github.com/nmattia/niv",
        "owner": "nmattia",
        "repo": "niv",
        "rev": "9d35b9e4837ab88517210b1701127612c260eccf",
        "sha256": "0q50xhnm8g2yfyakrh0nly4swyygxpi0a8cb9gp65wcakcgvzvdh",
        "type": "tarball",
        "url": "https://github.com/nmattia/niv/archive/9d35b9e4837ab88517210b1701127612c260eccf.tar.gz",
        "url_template": "https://github.com/<owner>/<repo>/archive/<rev>.tar.gz"
    },
    "nixpkgs": {
        "branch": "nixpkgs-unstable",
        "description": "Nix Packages collection",
        "homepage": null,
        "owner": "NixOS",
        "repo": "nixpkgs",
        "rev": "89281dd1dfed6839610f0ccad0c0e493606168fe",
        "sha256": "14jwgdqbhxf9581z9afzjzj0r0maw3m7227gn5bpk4fn8057vs5s",
        "type": "tarball",
        "url": "https://github.com/NixOS/nixpkgs/archive/89281dd1dfed6839610f0ccad0c0e493606168fe.tar.gz",
        "url_template": "https://github.com/<owner>/<repo>/archive/<rev>.tar.gz"
    }
}
